pyreinforce/__init__.py
pyreinforce/acting.py
pyreinforce/brain.py
pyreinforce/converter.py
pyreinforce/core.py
pyreinforce/ddpg.py
pyreinforce/memory.py
pyreinforce/montecarlo.py
pyreinforce/policygrad.py
pyreinforce/td.py
pyreinforce/utils.py
tests/__init__.py
tests/test_acting.py
tests/test_brain.py
tests/test_converter.py
tests/test_core.py
tests/test_ddpg.py
tests/test_memory.py
tests/test_montecarlo.py
tests/test_policygrad.py
tests/test_td.py
tests/test_utils.py
PyReinforce-0.2.dist-info/LICENSE
PyReinforce-0.2.dist-info/METADATA
PyReinforce-0.2.dist-info/WHEEL
PyReinforce-0.2.dist-info/top_level.txt
PyReinforce-0.2.dist-info/RECORD
